once/__init__.py
once/and_for_all/__init__.py
once/and_for_all/_base.py
once/and_for_all/_classes.py
once/and_for_all/_functions.py
once_and_for_all-0.1.0.dist-info/METADATA
once_and_for_all-0.1.0.dist-info/WHEEL
once_and_for_all-0.1.0.dist-info/RECORD
