Metadata-Version: 2.1
Name: once-and-for-all
Version: 0.1.0
Summary: A package for all streamlining enthusiasts. Apply universal Decorators and Metaclasses to your codebase.
Author: Simon Steinheber
Author-email: simon@steinheber.info
Requires-Python: >=3.10,<4
Classifier: Programming Language :: Python :: 3
Classifier: Programming Language :: Python :: 3.10
Classifier: Programming Language :: Python :: 3.11
Requires-Dist: isort (>=5.13.2,<6.0.0)
